Metadata-Version: 2.1
Name: Sip2
Version: 1.1
Summary: SIP2 Python Client: Simple Interchange Protocol Client for Python
Home-page: https://github.com/tzeumer/SIP2-Client-for-Python
Author: Tobias Zeumer
Author-email: tzeumer@verweisungsform.de
License: MIT
Platform: UNKNOWN
Classifier: Development Status :: 5 - Production/Stable
Classifier: Environment :: Console
Classifier: Operating System :: OS Independent
Classifier: Intended Audience :: Developers
Classifier: License :: OSI Approved :: MIT License
Classifier: Programming Language :: Python :: 3.4
Classifier: Topic :: Software Development :: Libraries
